pysilicon/__init__.py
pysilicon/binary.py
pysilicon/clkgen_driver.py
pysilicon/config.py
pysilicon/essentials.py
pysilicon/golden_models.py
pysilicon/scan_driver.py
pysilicon/utils.py
pysilicon/visa_driver.py
pysilicon-0.0.13.dist-info/LICENSE
pysilicon-0.0.13.dist-info/METADATA
pysilicon-0.0.13.dist-info/WHEEL
pysilicon-0.0.13.dist-info/top_level.txt
pysilicon-0.0.13.dist-info/RECORD
