Metadata-Version: 2.1
Name: pysilicon
Version: 0.0.13
Summary: A package with useful Python scripts for IC design and verification
Home-page: https://github.com/aoguzatli/pysilicon
Author: Oguz Atli
Author-email: aoguzatli@gmail.com
Classifier: Programming Language :: Python :: 3
Classifier: License :: OSI Approved :: MIT License
Classifier: Operating System :: OS Independent
Requires-Python: >=3.6
License-File: LICENSE
